LICENSE
dynamodb_session_flask/__init__.py
dynamodb_session_flask/_session.py
dynamodb_session_flask/py.typed
dynamodb_session_flask/testing.py
dynamodb_session_flask-1.1.3.dist-info/LICENSE
dynamodb_session_flask-1.1.3.dist-info/WHEEL
dynamodb_session_flask-1.1.3.dist-info/METADATA
dynamodb_session_flask-1.1.3.dist-info/RECORD
