Metadata-Version: 2.1
Name: dynamodb-session-flask
Version: 1.1.3
Summary: A session implementation for Flask using DynamoDB as a backing store and OWASP best practices for session management.
Home-page: https://github.com/JCapriotti/dynamodb-session-flask
License: MIT
Keywords: flask,session,DynamoDB
Author: Jason Capriotti
Author-email: jason.capriotti@gmail.com
Requires-Python: >=3.7,<4.0
Classifier: License :: OSI Approved :: MIT License
Classifier: Programming Language :: Python :: 3
Classifier: Programming Language :: Python :: 3.7
Classifier: Programming Language :: Python :: 3.8
Classifier: Programming Language :: Python :: 3.9
Classifier: Programming Language :: Python :: 3.10
Requires-Dist: Flask (>=2.0.0,<3.0.0)
Requires-Dist: dynamodb-session-web (>=0.2.7,<0.3.0)
Project-URL: Repository, https://github.com/JCapriotti/dynamodb-session-flask
